flordb/__init__.py
flordb/__main__.py
flordb/api.py
flordb/cli.py
flordb/clock.py
flordb/constants.py
flordb/database.py
flordb/obj_store.py
flordb/orm.py
flordb/repl.py
flordb/utils.py
flordb/versions.py
flordb/hlast/__init__.py
flordb/hlast/gtpropagate.py
flordb/hlast/visitors.py
flordb/hlast/gumtree/__init__.py
flordb/hlast/gumtree/adapter.py
flordb/hlast/gumtree/idmap.py
flordb/hlast/gumtree/priorityq.py
flordb/hlast/gumtree/python.py
flordb/hlast/gumtree/test.py
flordb/hlast/gumtree/tree.py
flordb-3.4.12.dist-info/METADATA
flordb-3.4.12.dist-info/WHEEL
flordb-3.4.12.dist-info/top_level.txt
flordb-3.4.12.dist-info/RECORD
