Metadata-Version: 2.4
Name: flordb
Version: 3.4.12
Summary: A hindsight logging dataabase for MLOps
Home-page: https://github.com/ucbrise/flor
Author: Rolando Garcia
Author-email: rolando.garcia@asu.edu
Classifier: Programming Language :: Python :: 3
Classifier: License :: OSI Approved :: Apache Software License
Classifier: Operating System :: OS Independent
Requires-Python: >=3.9
Requires-Dist: GitPython
Requires-Dist: cloudpickle
Requires-Dist: astunparse
Requires-Dist: pandas
Requires-Dist: bidict==0.21.3
Requires-Dist: apted
Requires-Dist: matplotlib
Requires-Dist: scikit-learn
Requires-Dist: numpy
Requires-Dist: tqdm
Requires-Dist: sh
Requires-Dist: ipython
Requires-Dist: ipykernel
Dynamic: author
Dynamic: author-email
Dynamic: classifier
Dynamic: description
Dynamic: description-content-type
Dynamic: home-page
Dynamic: requires-dist
Dynamic: requires-python
Dynamic: summary
